pycompall.py
app/__init__.py
app/__main__.py
app/application.py
app/__pycache__/__init__.cpython-310.pyc
app/__pycache__/application.cpython-310.pyc
pycompall-0.2.0.dist-info/LICENSE
pycompall-0.2.0.dist-info/METADATA
pycompall-0.2.0.dist-info/WHEEL
pycompall-0.2.0.dist-info/entry_points.txt
pycompall-0.2.0.dist-info/top_level.txt
pycompall-0.2.0.dist-info/RECORD
