Metadata-Version: 2.1
Name: pycompall
Version: 0.2.0
Summary: Pycompall is a wrapper around the default `compileall` Python utility to compile `.py` to `.pyc` files to provide a more configurable interface and as a build tool when configuring python files.
Author-email: Kim Yongbeom <yongbeom.kim@u.nus.edu>
Project-URL: Homepage, https://github.com/Yongbeom-Kim/py-compiler
Project-URL: Repository, https://github.com/Yongbeom-Kim/py-compiler
Keywords: obfuscation,python-obfuscation,python-compiler
Classifier: Programming Language :: Python :: 3.11
Classifier: Operating System :: OS Independent
Requires-Python: >=3.7
License-File: LICENSE
Requires-Dist: click (>=7.1.2)
Requires-Dist: attrs (>=22)
